reference/__init__.py
refvars/__init__.py
refvars/mem_win_x86.py
refvars/mem_win_x86_lib.dll
refvars-0.7.dist-info/LICENCE
refvars-0.7.dist-info/METADATA
refvars-0.7.dist-info/WHEEL
refvars-0.7.dist-info/top_level.txt
refvars-0.7.dist-info/RECORD
