Metadata-Version: 2.1
Name: refvars
Version: 0.7
Summary: Solving one of Python's biggest problems. Reference types (output variables) are not implemented.
Author: matrikater (Joel C. Watson)
Author-email: matrikater@matriko.xyz
Keywords: python,reference,variables,pointers,output,return,types,reference types,refvars
Classifier: Development Status :: 3 - Alpha
Classifier: Intended Audience :: Developers
Classifier: Programming Language :: Python :: 3
Classifier: Operating System :: OS Independent
Classifier: Natural Language :: English
Classifier: Topic :: Software Development :: Libraries :: Python Modules
License-File: LICENCE
